dfm_python/__init__.py
dfm_python/config/__init__.py
dfm_python/config/adapter.py
dfm_python/config/constants.py
dfm_python/config/types.py
dfm_python/config/schema/__init__.py
dfm_python/config/schema/block.py
dfm_python/config/schema/model.py
dfm_python/config/schema/params.py
dfm_python/config/schema/results.py
dfm_python/dataset/__init__.py
dfm_python/dataset/ddfm_dataset.py
dfm_python/dataset/dfm_dataset.py
dfm_python/dataset/time.py
dfm_python/decoder/__init__.py
dfm_python/decoder/base.py
dfm_python/decoder/linear.py
dfm_python/decoder/mlp.py
dfm_python/encoder/__init__.py
dfm_python/encoder/base.py
dfm_python/encoder/pca.py
dfm_python/encoder/simple_autoencoder.py
dfm_python/functional/__init__.py
dfm_python/functional/dfm_block.py
dfm_python/functional/em.py
dfm_python/logger/__init__.py
dfm_python/logger/inference_logger.py
dfm_python/logger/logger.py
dfm_python/logger/train_logger.py
dfm_python/models/__init__.py
dfm_python/models/base.py
dfm_python/models/ddfm.py
dfm_python/models/dfm.py
dfm_python/numeric/builder.py
dfm_python/numeric/estimator.py
dfm_python/numeric/stability.py
dfm_python/numeric/statistic.py
dfm_python/numeric/tent.py
dfm_python/numeric/validator.py
dfm_python/ssm/__init__.py
dfm_python/ssm/kalman.py
dfm_python/utils/__init__.py
dfm_python/utils/checkpoint.py
dfm_python/utils/errors.py
dfm_python/utils/helper.py
dfm_python/utils/loss.py
dfm_python/utils/metric.py
dfm_python/utils/misc.py
dfm_python/utils/validation.py
dfm_python-0.5.58.dist-info/METADATA
dfm_python-0.5.58.dist-info/WHEEL
dfm_python-0.5.58.dist-info/RECORD
