Metadata-Version: 2.4
Name: dfm-python
Version: 0.5.58
Summary: Dynamic Factor Model (DFM) estimation and forecasting in Python
Project-URL: Homepage, https://github.com/yourusername/dfm-python
Project-URL: Documentation, https://github.com/yourusername/dfm-python#readme
Project-URL: Repository, https://github.com/yourusername/dfm-python
Project-URL: Issues, https://github.com/yourusername/dfm-python/issues
Author: Minkey Chang
License: MIT
Keywords: dfm,dynamic-factor-model,econometrics,forecasting,time-series
Classifier: Development Status :: 4 - Beta
Classifier: Intended Audience :: Science/Research
Classifier: License :: OSI Approved :: MIT License
Classifier: Programming Language :: Python :: 3
Classifier: Programming Language :: Python :: 3.10
Classifier: Programming Language :: Python :: 3.11
Classifier: Programming Language :: Python :: 3.12
Classifier: Topic :: Scientific/Engineering
Requires-Python: >=3.10
Requires-Dist: einops>=0.8.1
Requires-Dist: hydra-core>=1.3.2
Requires-Dist: matplotlib>=3.5.0
Requires-Dist: numpy>=1.24.0
Requires-Dist: pandas>=2.0.0
Requires-Dist: pyarrow>=22.0.0
Requires-Dist: pykalman>=0.11.0
Requires-Dist: pytorch-lightning>=2.0.0
Requires-Dist: scikit-learn>=1.7.2
Requires-Dist: scipy>=1.10.0
Requires-Dist: sktime>=0.40.1
Requires-Dist: torch>=2.0.0
Requires-Dist: twine>=6.2.0
Provides-Extra: all
Requires-Dist: hydra-core>=1.3.0; extra == 'all'
Requires-Dist: omegaconf>=2.3.0; extra == 'all'
Requires-Dist: pytest-cov>=4.0.0; extra == 'all'
Requires-Dist: pytest>=7.0.0; extra == 'all'
Requires-Dist: scikit-learn>=1.0.0; extra == 'all'
Requires-Dist: sktime>=0.27.0; extra == 'all'
Requires-Dist: sqlalchemy>=2.0.0; extra == 'all'
Provides-Extra: db
Requires-Dist: sqlalchemy>=2.0.0; extra == 'db'
Provides-Extra: deep
Provides-Extra: dev
Requires-Dist: pytest-cov>=4.0.0; extra == 'dev'
Requires-Dist: pytest>=7.0.0; extra == 'dev'
Requires-Dist: scikit-learn>=1.0.0; extra == 'dev'
Provides-Extra: forecasting
Requires-Dist: sktime[forecasting]>=0.40.1; extra == 'forecasting'
Provides-Extra: hydra
Requires-Dist: hydra-core>=1.3.0; extra == 'hydra'
Requires-Dist: omegaconf>=2.3.0; extra == 'hydra'
Provides-Extra: transform
Requires-Dist: sktime>=0.27.0; extra == 'transform'
